motmetrics/__init__.py
motmetrics/distances.py
motmetrics/io.py
motmetrics/lap.py
motmetrics/math_util.py
motmetrics/metrics.py
motmetrics/mot.py
motmetrics/preprocess.py
motmetrics/utils.py
motmetrics/apps/__init__.py
motmetrics/apps/eval_detrac.py
motmetrics/apps/eval_motchallenge.py
motmetrics/apps/evaluateTracking.py
motmetrics/apps/example.py
motmetrics/apps/list_metrics.py
motmetrics/data/TUD-Campus/gt.txt
motmetrics/data/TUD-Campus/test.txt
motmetrics/data/TUD-Stadtmitte/gt.txt
motmetrics/data/TUD-Stadtmitte/test.txt
motmetrics/data/iotest/detrac.mat
motmetrics/data/iotest/detrac.xml
motmetrics/data/iotest/motchallenge.txt
motmetrics/data/iotest/vatic.txt
motmetrics/etc/mot.png
motmetrics/tests/__init__.py
motmetrics/tests/test_distances.py
motmetrics/tests/test_io.py
motmetrics/tests/test_issue19.py
motmetrics/tests/test_lap.py
motmetrics/tests/test_metrics.py
motmetrics/tests/test_mot.py
motmetrics/tests/test_utils.py
motmetrics-1.2.5.dist-info/LICENSE
motmetrics-1.2.5.dist-info/METADATA
motmetrics-1.2.5.dist-info/WHEEL
motmetrics-1.2.5.dist-info/top_level.txt
motmetrics-1.2.5.dist-info/RECORD
