Metadata-Version: 2.1
Name: motmetrics
Version: 1.2.5
Summary: Metrics for multiple object tracker benchmarking.
Home-page: https://github.com/cheind/py-motmetrics
Author: Christoph Heindl, Jack Valmadre
License: MIT
Keywords: tracker MOT evaluation metrics compare
Platform: UNKNOWN
License-File: LICENSE
Requires-Dist: numpy (>=1.12.1)
Requires-Dist: pandas (>=0.23.1)
Requires-Dist: scipy (>=0.19.0)
Requires-Dist: xmltodict (>=0.12.0)
Requires-Dist: enum34 ; python_version < "3"
